[
  {
    "date": "2026-06-03",
    "level": "easy",
    "words": [
      "IN",
      "CHANCE",
      "WHERE",
      "UP",
      "DIE",
      "CROWDED",
      "HI",
      "HIS",
      "LARGE",
      "ASLEEP",
      "FLY",
      "NEAR",
      "OF",
      "FAN",
      "CAREFUL",
      "EGG",
      "ANY",
      "BE",
      "NO"
    ]
  },
  {
    "date": "2026-06-03",
    "level": "medium",
    "words": [
      "MY",
      "FUNDING",
      "LABEL",
      "AN",
      "USE",
      "FAILURE",
      "US",
      "ASK",
      "NO",
      "BEG",
      "ROW",
      "FEE",
      "DARE",
      "IF",
      "AID",
      "ISOLATE",
      "NOW",
      "ICE",
      "GO",
      "DO"
    ]
  },
  {
    "date": "2026-06-03",
    "level": "hard",
    "words": [
      "DO",
      "CURTAIN",
      "SPITE",
      "BE",
      "TON",
      "CLUSTER",
      "US",
      "POP",
      "MASK",
      "REMIND",
      "YET",
      "THAT",
      "BY",
      "NOW",
      "ABSENCE",
      "INK",
      "OPT",
      "NO",
      "WE"
    ]
  },
  {
    "date": "2026-06-04",
    "level": "easy",
    "words": [
      "AN",
      "HIMSELF",
      "IDEA",
      "ID",
      "DENTIST",
      "HOLIDAY",
      "IT",
      "DEW",
      "METER",
      "MOMENT",
      "RED",
      "SWEATER",
      "EAT",
      "ICE",
      "LIE",
      "SAD",
      "FIR",
      "TV"
    ]
  },
  {
    "date": "2026-06-04",
    "level": "medium",
    "words": [
      "US",
      "COURAGE",
      "SEED",
      "SO",
      "INSIGHT",
      "CONSIST",
      "OF",
      "END",
      "LATTE",
      "UNLESS",
      "GYM",
      "READING",
      "ACT",
      "GUY",
      "GET",
      "HIM",
      "EVE",
      "TO"
    ]
  },
  {
    "date": "2026-06-04",
    "level": "hard",
    "words": [
      "AD",
      "CHATTER",
      "CLOG",
      "BY",
      "KINGDOM",
      "CRACKLE",
      "HI",
      "LIP",
      "MIXED",
      "ALMOND",
      "ROD",
      "TRIGGER",
      "TAX",
      "DUO",
      "EVE",
      "ODD",
      "RID",
      "MY"
    ]
  },
  {
    "date": "2026-06-05",
    "level": "easy",
    "words": [
      "GO",
      "CONNECT",
      "CHASM",
      "AS",
      "EAR",
      "CONCERT",
      "ON",
      "HAT",
      "NO",
      "ART",
      "WAY",
      "YEN",
      "NEWS",
      "BY",
      "PUT",
      "EXAMPLE",
      "CRY",
      "URN",
      "TO",
      "TV"
    ]
  },
  {
    "date": "2026-06-06",
    "level": "easy",
    "words": [
      "ME",
      "SAUSAGE",
      "MODEL",
      "IS",
      "MARRIED",
      "SHIMMER",
      "AT",
      "OAR",
      "UP",
      "DRY",
      "VINE",
      "LYE",
      "SEVERAL",
      "ABILITY",
      "GUN",
      "EYE",
      "EVE",
      "DO"
    ]
  },
  {
    "date": "2026-06-07",
    "level": "easy",
    "words": [
      "AN",
      "FORWARD",
      "SWIRL",
      "BY",
      "TIP",
      "FIRSTLY",
      "OF",
      "WIN",
      "CARE",
      "RECIPE",
      "PEN",
      "WEAR",
      "UP",
      "ITS",
      "AIRLINE",
      "RYE",
      "TEN",
      "DO",
      "SO"
    ]
  },
  {
    "date": "2026-06-08",
    "level": "easy",
    "words": [
      "US",
      "FOREST",
      "METRE",
      "GO",
      "ILL",
      "FARMING",
      "OF",
      "ELM",
      "SEVEN",
      "RUSTLE",
      "DYE",
      "EVER",
      "CD",
      "NAB",
      "SEVENTY",
      "TIE",
      "ALE",
      "IN",
      "BY"
    ]
  },
  {
    "date": "2026-06-09",
    "level": "easy",
    "words": [
      "OR",
      "STOMACH",
      "THIN",
      "ME",
      "TONIGHT",
      "SCATTER",
      "TV",
      "HOW",
      "LATTE",
      "ONLINE",
      "GYM",
      "MEANING",
      "ACT",
      "GUY",
      "CAT",
      "HUM",
      "HUE",
      "TO"
    ]
  },
  {
    "date": "2026-06-10",
    "level": "easy",
    "words": [
      "TV",
      "MAGENTA",
      "SHEET",
      "BE",
      "OIL",
      "MONSOON",
      "AS",
      "HIM",
      "GO",
      "ELF",
      "SIP",
      "TRY",
      "ELSE",
      "AT",
      "HIT",
      "NEITHER",
      "TOP",
      "IVY",
      "AN",
      "TO"
    ]
  },
  {
    "date": "2026-06-05",
    "level": "medium",
    "words": [
      "ME",
      "CUSTARD",
      "REFER",
      "HI",
      "ILL",
      "CHERISH",
      "US",
      "ELM",
      "SO",
      "FLY",
      "PEN",
      "YET",
      "TAPE",
      "BY",
      "ARM",
      "AVERAGE",
      "RUN",
      "RAT",
      "DO",
      "MY"
    ]
  },
  {
    "date": "2026-06-06",
    "level": "medium",
    "words": [
      "OF",
      "MONITOR",
      "SNEER",
      "OR",
      "TARNISH",
      "MONSTER",
      "OK",
      "NAG",
      "NO",
      "ERA",
      "TREE",
      "EYE",
      "INTENSE",
      "TERRIFY",
      "OWE",
      "SEE",
      "RYE",
      "HE"
    ]
  },
  {
    "date": "2026-06-07",
    "level": "medium",
    "words": [
      "AD",
      "KILLING",
      "CRAFT",
      "BE",
      "HAT",
      "KITCHEN",
      "ID",
      "RAW",
      "CAST",
      "LOCATE",
      "ITS",
      "LEAF",
      "HI",
      "AGO",
      "INSTANT",
      "NOT",
      "GAS",
      "GO",
      "OF"
    ]
  },
  {
    "date": "2026-06-08",
    "level": "medium",
    "words": [
      "UP",
      "COURSE",
      "FAINT",
      "HE",
      "INK",
      "CONFIRM",
      "ON",
      "AND",
      "LITRE",
      "UNLIKE",
      "FRY",
      "REIN",
      "OF",
      "LAW",
      "SETTLER",
      "EAR",
      "ANY",
      "ME",
      "WE"
    ]
  },
  {
    "date": "2026-06-09",
    "level": "medium",
    "words": [
      "OR",
      "VISIBLE",
      "VOTE",
      "ME",
      "ELEGANT",
      "VELVETY",
      "IN",
      "OLD",
      "SLEET",
      "SISTER",
      "LET",
      "ILLEGAL",
      "BEE",
      "AGE",
      "LIE",
      "NIT",
      "EAT",
      "TV"
    ]
  },
  {
    "date": "2026-06-10",
    "level": "medium",
    "words": [
      "DO",
      "CONFESS",
      "THEME",
      "AT",
      "EEL",
      "CONTEST",
      "OR",
      "HER",
      "NO",
      "ELF",
      "ADD",
      "DYE",
      "FOAM",
      "ID",
      "ROB",
      "ELDERLY",
      "SAD",
      "ONE",
      "SO",
      "BY"
    ]
  },
  {
    "date": "2026-06-05",
    "level": "hard",
    "words": [
      "ON",
      "HUNTING",
      "EASEL",
      "TO",
      "SIP",
      "HONESTY",
      "UP",
      "AIM",
      "NO",
      "SPY",
      "MOB",
      "FEE",
      "TIME",
      "OF",
      "ACT",
      "ISOLATE",
      "NAB",
      "CUE",
      "GO",
      "TV"
    ]
  },
  {
    "date": "2026-06-06",
    "level": "hard",
    "words": [
      "TV",
      "CHAPTER",
      "SCANT",
      "IF",
      "TUITION",
      "CRYSTAL",
      "HI",
      "CUT",
      "AT",
      "AID",
      "ISLE",
      "DYE",
      "POINTED",
      "TESTIFY",
      "EEL",
      "OWE",
      "RYE",
      "NO"
    ]
  },
  {
    "date": "2026-06-07",
    "level": "hard",
    "words": [
      "OR",
      "FOLDING",
      "ADAPT",
      "BE",
      "NOR",
      "FINANCE",
      "OF",
      "DOT",
      "ZEST",
      "LIZARD",
      "ELM",
      "DEEP",
      "WE",
      "ASH",
      "INSTALL",
      "NET",
      "SUM",
      "GO",
      "HE"
    ]
  },
  {
    "date": "2026-06-08",
    "level": "hard",
    "words": [
      "AS",
      "DISMAL",
      "CATER",
      "US",
      "AWL",
      "DISCARD",
      "ID",
      "AWE",
      "BREED",
      "SUBTLE",
      "SET",
      "MERE",
      "IS",
      "ARM",
      "AVERAGE",
      "LIE",
      "RAT",
      "AD",
      "MY"
    ]
  },
  {
    "date": "2026-06-09",
    "level": "hard",
    "words": [
      "ME",
      "COASTAL",
      "CLUE",
      "OF",
      "EASTERN",
      "CONCEDE",
      "ON",
      "LAY",
      "CREEP",
      "ACCUSE",
      "HAM",
      "STRETCH",
      "TOE",
      "ERA",
      "AXE",
      "RAM",
      "LAP",
      "NO"
    ]
  },
  {
    "date": "2026-06-10",
    "level": "hard",
    "words": [
      "UP",
      "CUSTARD",
      "IMAGE",
      "AD",
      "COG",
      "CYNICAL",
      "US",
      "MOO",
      "SO",
      "AGE",
      "IVY",
      "YEN",
      "TWIG",
      "BY",
      "RUB",
      "ADVERSE",
      "RAY",
      "URN",
      "DO",
      "BE"
    ]
  },
  {
    "date": "2026-06-11",
    "level": "easy",
    "words": [
      "AT",
      "MUSTARD",
      "TOWER",
      "MY",
      "AWE",
      "MISTAKE",
      "UP",
      "OWN",
      "OPEN",
      "SHOWER",
      "YET",
      "TYPE",
      "BY",
      "AGO",
      "AVERAGE",
      "RUN",
      "GET",
      "DO",
      "ON"
    ]
  },
  {
    "date": "2026-06-11",
    "level": "medium",
    "words": [
      "AN",
      "ATTRACT",
      "AWFUL",
      "BY",
      "MILLION",
      "ASHAMED",
      "TV",
      "WIN",
      "TO",
      "FLU",
      "GREY",
      "RED",
      "REGULAR",
      "AIRLINE",
      "CUE",
      "ODD",
      "TOY",
      "NO"
    ]
  },
  {
    "date": "2026-06-11",
    "level": "hard",
    "words": [
      "UP",
      "BACKUP",
      "SHINE",
      "IN",
      "TIN",
      "BLISTER",
      "AS",
      "HIP",
      "SEDGE",
      "CASINO",
      "FOE",
      "KEEN",
      "IF",
      "RAW",
      "UNDERGO",
      "PEG",
      "ALE",
      "ME",
      "WE"
    ]
  }
]